odoo10_addon_project_task_default_stage-10.0.1.1.0-py2.7-nspkg.pth
odoo/addons/project_task_default_stage/README.rst
odoo/addons/project_task_default_stage/__init__.py
odoo/addons/project_task_default_stage/__manifest__.py
odoo/addons/project_task_default_stage/data/project_data.xml
odoo/addons/project_task_default_stage/i18n/de.po
odoo/addons/project_task_default_stage/i18n/es.po
odoo/addons/project_task_default_stage/i18n/es_MX.po
odoo/addons/project_task_default_stage/i18n/fi.po
odoo/addons/project_task_default_stage/i18n/fr.po
odoo/addons/project_task_default_stage/i18n/hr.po
odoo/addons/project_task_default_stage/i18n/nl.po
odoo/addons/project_task_default_stage/i18n/nl_NL.po
odoo/addons/project_task_default_stage/i18n/pt.po
odoo/addons/project_task_default_stage/i18n/pt_BR.po
odoo/addons/project_task_default_stage/i18n/pt_PT.po
odoo/addons/project_task_default_stage/i18n/sl.po
odoo/addons/project_task_default_stage/i18n/tr.po
odoo/addons/project_task_default_stage/i18n/zh_CN.po
odoo/addons/project_task_default_stage/models/__init__.py
odoo/addons/project_task_default_stage/models/project.py
odoo/addons/project_task_default_stage/models/project_task_type.py
odoo/addons/project_task_default_stage/static/description/icon.png
odoo/addons/project_task_default_stage/tests/__init__.py
odoo/addons/project_task_default_stage/tests/test_project_task_default_stage.py
odoo/addons/project_task_default_stage/views/project_view.xml
odoo10_addon_project_task_default_stage-10.0.1.1.0.dist-info/DESCRIPTION.rst
odoo10_addon_project_task_default_stage-10.0.1.1.0.dist-info/METADATA
odoo10_addon_project_task_default_stage-10.0.1.1.0.dist-info/RECORD
odoo10_addon_project_task_default_stage-10.0.1.1.0.dist-info/WHEEL
odoo10_addon_project_task_default_stage-10.0.1.1.0.dist-info/metadata.json
odoo10_addon_project_task_default_stage-10.0.1.1.0.dist-info/namespace_packages.txt
odoo10_addon_project_task_default_stage-10.0.1.1.0.dist-info/top_level.txt
